pipeline/DataMemory.v
module DataMemory #(parameter mem_size=256, parameter log_mem_size=8) (clk, address, outputf);

output [log_mem_size-1 : 0] outputf;
reg [log_mem_size-1 : 0] data [0 : mem_size-1];
input wire [log_mem_size-1 : 0] address;
input clk;

integer i;
initial begin
    for (i=0; i<mem_size; i = i +1) begin
        data[i] = 0;
    end
    data[1] = 2;
    data[6] = 66;
    data[8] = 1;
end

assign outputf = data[address];


endmodule //DataMemory

pipeline/DataMemory_tb.v
//auto generated test by : MR_X
//Dec:14:2020
`include "DataMemory.v"
module DataMemory_tb #(parameter mem_size=256, parameter log_mem_size=8) ();
initial begin
$dumpfile("DataMemory.vcd");
$dumpvars(0, DataMemory_tb);
end

wire [log_mem_size-1 : 0] outputf;
reg [log_mem_size-1 : 0] address;
reg clk;

initial clk = 0;
always #20 clk = ~clk;
//make new instance of module here
DataMemory #(.mem_size(mem_size) , .log_mem_size(log_mem_size)) instance1(clk, address, outputf);
initial
begin

address = 5;
#40;

address = 6;
#40;

address = 1;
#40;

address = 8;
#40;

$finish;
end
endmodule //DataMemory_tb

pipeline/DataMemory.vcd
$date
	Mon Dec 14 11:23:59 2020
$end
$version
	Icarus Verilog
$end
$timescale
	1s
$end
$scope module DataMemory_tb $end
$var wire 8 ! outputf [7:0] $end
$var reg 8 " address [7:0] $end
$var reg 1 # clk $end
$scope module instance1 $end
$var wire 8 $ address [7:0] $end
$var wire 1 # clk $end
$var reg 8 % outputf [7:0] $end
$var integer 32 & i [31:0] $end
$upscope $end
$upscope $end
$enddefinitions $end
#0
$dumpvars
b100000000 &
bx %
b101 $
0#
b101 "
bx !
$end
#20
b0 !
b0 %
1#
#40
0#
b110 "
b110 $
#60
b1000010 !
b1000010 %
1#
#80
0#
b1 "
b1 $
#100
b0 !
b0 %
1#
#120
0#
b1000 "
b1000 $
#140
b1 !
b1 %
1#
